{"prefix":"onprem","width":64,"height":64,"icons":{"aggregator-fluentd":{"path":"icons/onprem/aggregator/fluentd.png","category":"aggregator"},"aggregator-vector":{"path":"icons/onprem/aggregator/vector.png","category":"aggregator"},"analytics-beam":{"path":"icons/onprem/analytics/beam.png","category":"analytics"},"analytics-databricks":{"path":"icons/onprem/analytics/databricks.png","category":"analytics"},"analytics-dbt":{"path":"icons/onprem/analytics/dbt.png","category":"analytics"},"analytics-dremio":{"path":"icons/onprem/analytics/dremio.png","category":"analytics"},"analytics-flink":{"path":"icons/onprem/analytics/flink.png","category":"analytics"},"analytics-hadoop":{"path":"icons/onprem/analytics/hadoop.png","category":"analytics"},"analytics-hive":{"path":"icons/onprem/analytics/hive.png","category":"analytics"},"analytics-metabase":{"path":"icons/onprem/analytics/metabase.png","category":"analytics"},"analytics-norikra":{"path":"icons/onprem/analytics/norikra.png","category":"analytics"},"analytics-powerbi":{"path":"icons/onprem/analytics/powerbi.png","category":"analytics"},"analytics-presto":{"path":"icons/onprem/analytics/presto.png","category":"analytics"},"analytics-singer":{"path":"icons/onprem/analytics/singer.png","category":"analytics"},"analytics-spark":{"path":"icons/onprem/analytics/spark.png","category":"analytics"},"analytics-storm":{"path":"icons/onprem/analytics/storm.png","category":"analytics"},"analytics-superset":{"path":"icons/onprem/analytics/superset.png","category":"analytics"},"analytics-tableau":{"path":"icons/onprem/analytics/tableau.png","category":"analytics"},"analytics-trino":{"path":"icons/onprem/analytics/trino.png","category":"analytics"},"auth-boundary":{"path":"icons/onprem/auth/boundary.png","category":"auth"},"auth-buzzfeed-sso":{"path":"icons/onprem/auth/buzzfeed-sso.png","category":"auth"},"auth-oauth2-proxy":{"path":"icons/onprem/auth/oauth2-proxy.png","category":"auth"},"cd-spinnaker":{"path":"icons/onprem/cd/spinnaker.png","category":"cd"},"cd-tekton":{"path":"icons/onprem/cd/tekton.png","category":"cd"},"cd-tekton-cli":{"path":"icons/onprem/cd/tekton-cli.png","category":"cd"},"certificates-cert-manager":{"path":"icons/onprem/certificates/cert-manager.png","category":"certificates"},"certificates-lets-encrypt":{"path":"icons/onprem/certificates/lets-encrypt.png","category":"certificates"},"ci-circleci":{"path":"icons/onprem/ci/circleci.png","category":"ci"},"ci-concourseci":{"path":"icons/onprem/ci/concourseci.png","category":"ci"},"ci-droneci":{"path":"icons/onprem/ci/droneci.png","category":"ci"},"ci-github-actions":{"path":"icons/onprem/ci/github-actions.png","category":"ci"},"ci-gitlabci":{"path":"icons/onprem/ci/gitlabci.png","category":"ci"},"ci-jenkins":{"path":"icons/onprem/ci/jenkins.png","category":"ci"},"ci-teamcity":{"path":"icons/onprem/ci/teamcity.png","category":"ci"},"ci-travisci":{"path":"icons/onprem/ci/travisci.png","category":"ci"},"ci-zuulci":{"path":"icons/onprem/ci/zuulci.png","category":"ci"},"client-client":{"path":"icons/onprem/client/client.png","category":"client"},"client-user":{"path":"icons/onprem/client/user.png","category":"client"},"client-users":{"path":"icons/onprem/client/users.png","category":"client"},"compute-nomad":{"path":"icons/onprem/compute/nomad.png","category":"compute"},"compute-server":{"path":"icons/onprem/compute/server.png","category":"compute"},"container-containerd":{"path":"icons/onprem/container/containerd.png","category":"container"},"container-crio":{"path":"icons/onprem/container/crio.png","category":"container"},"container-docker":{"path":"icons/onprem/container/docker.png","category":"container"},"container-firecracker":{"path":"icons/onprem/container/firecracker.png","category":"container"},"container-gvisor":{"path":"icons/onprem/container/gvisor.png","category":"container"},"container-k3s":{"path":"icons/onprem/container/k3s.png","category":"container"},"container-lxc":{"path":"icons/onprem/container/lxc.png","category":"container"},"container-rkt":{"path":"icons/onprem/container/rkt.png","category":"container"},"database-cassandra":{"path":"icons/onprem/database/cassandra.png","category":"database"},"database-clickhouse":{"path":"icons/onprem/database/clickhouse.png","category":"database"},"database-cockroachdb":{"path":"icons/onprem/database/cockroachdb.png","category":"database"},"database-couchbase":{"path":"icons/onprem/database/couchbase.png","category":"database"},"database-couchdb":{"path":"icons/onprem/database/couchdb.png","category":"database"},"database-dgraph":{"path":"icons/onprem/database/dgraph.png","category":"database"},"database-druid":{"path":"icons/onprem/database/druid.png","category":"database"},"database-duckdb":{"path":"icons/onprem/database/duckdb.png","category":"database"},"database-hbase":{"path":"icons/onprem/database/hbase.png","category":"database"},"database-influxdb":{"path":"icons/onprem/database/influxdb.png","category":"database"},"database-janusgraph":{"path":"icons/onprem/database/janusgraph.png","category":"database"},"database-mariadb":{"path":"icons/onprem/database/mariadb.png","category":"database"},"database-mongodb":{"path":"icons/onprem/database/mongodb.png","category":"database"},"database-mssql":{"path":"icons/onprem/database/mssql.png","category":"database"},"database-mysql":{"path":"icons/onprem/database/mysql.png","category":"database"},"database-neo4j":{"path":"icons/onprem/database/neo4j.png","category":"database"},"database-oracle":{"path":"icons/onprem/database/oracle.png","category":"database"},"database-postgresql":{"path":"icons/onprem/database/postgresql.png","category":"database"},"database-qdrant":{"path":"icons/onprem/database/qdrant.png","category":"database"},"database-scylla":{"path":"icons/onprem/database/scylla.png","category":"database"},"dns-coredns":{"path":"icons/onprem/dns/coredns.png","category":"dns"},"dns-powerdns":{"path":"icons/onprem/dns/powerdns.png","category":"dns"},"etl-embulk":{"path":"icons/onprem/etl/embulk.png","category":"etl"},"gitops-argocd":{"path":"icons/onprem/gitops/argocd.png","category":"gitops"},"gitops-flagger":{"path":"icons/onprem/gitops/flagger.png","category":"gitops"},"gitops-flux":{"path":"icons/onprem/gitops/flux.png","category":"gitops"},"groupware-nextcloud":{"path":"icons/onprem/groupware/nextcloud.png","category":"groupware"},"iac-ansible":{"path":"icons/onprem/iac/ansible.png","category":"iac"},"iac-atlantis":{"path":"icons/onprem/iac/atlantis.png","category":"iac"},"iac-awx":{"path":"icons/onprem/iac/awx.png","category":"iac"},"iac-pulumi":{"path":"icons/onprem/iac/pulumi.png","category":"iac"},"iac-puppet":{"path":"icons/onprem/iac/puppet.png","category":"iac"},"iac-terraform":{"path":"icons/onprem/iac/terraform.png","category":"iac"},"identity-dex":{"path":"icons/onprem/identity/dex.png","category":"identity"},"inmemory-aerospike":{"path":"icons/onprem/inmemory/aerospike.png","category":"inmemory"},"inmemory-hazelcast":{"path":"icons/onprem/inmemory/hazelcast.png","category":"inmemory"},"inmemory-memcached":{"path":"icons/onprem/inmemory/memcached.png","category":"inmemory"},"inmemory-redis":{"path":"icons/onprem/inmemory/redis.png","category":"inmemory"},"logging-fluentbit":{"path":"icons/onprem/logging/fluentbit.png","category":"logging"},"logging-graylog":{"path":"icons/onprem/logging/graylog.png","category":"logging"},"logging-loki":{"path":"icons/onprem/logging/loki.png","category":"logging"},"logging-rsyslog":{"path":"icons/onprem/logging/rsyslog.png","category":"logging"},"logging-syslog-ng":{"path":"icons/onprem/logging/syslog-ng.png","category":"logging"},"messaging-centrifugo":{"path":"icons/onprem/messaging/centrifugo.png","category":"messaging"},"mlops-mlflow":{"path":"icons/onprem/mlops/mlflow.png","category":"mlops"},"mlops-polyaxon":{"path":"icons/onprem/mlops/polyaxon.png","category":"mlops"},"monitoring-cortex":{"path":"icons/onprem/monitoring/cortex.png","category":"monitoring"},"monitoring-datadog":{"path":"icons/onprem/monitoring/datadog.png","category":"monitoring"},"monitoring-dynatrace":{"path":"icons/onprem/monitoring/dynatrace.png","category":"monitoring"},"monitoring-grafana":{"path":"icons/onprem/monitoring/grafana.png","category":"monitoring"},"monitoring-humio":{"path":"icons/onprem/monitoring/humio.png","category":"monitoring"},"monitoring-mimir":{"path":"icons/onprem/monitoring/mimir.png","category":"monitoring"},"monitoring-nagios":{"path":"icons/onprem/monitoring/nagios.png","category":"monitoring"},"monitoring-newrelic":{"path":"icons/onprem/monitoring/newrelic.png","category":"monitoring"},"monitoring-prometheus":{"path":"icons/onprem/monitoring/prometheus.png","category":"monitoring"},"monitoring-prometheus-operator":{"path":"icons/onprem/monitoring/prometheus-operator.png","category":"monitoring"},"monitoring-sentry":{"path":"icons/onprem/monitoring/sentry.png","category":"monitoring"},"monitoring-splunk":{"path":"icons/onprem/monitoring/splunk.png","category":"monitoring"},"monitoring-thanos":{"path":"icons/onprem/monitoring/thanos.png","category":"monitoring"},"monitoring-zabbix":{"path":"icons/onprem/monitoring/zabbix.png","category":"monitoring"},"network-ambassador":{"path":"icons/onprem/network/ambassador.png","category":"network"},"network-apache":{"path":"icons/onprem/network/apache.png","category":"network"},"network-bind-9":{"path":"icons/onprem/network/bind-9.png","category":"network"},"network-caddy":{"path":"icons/onprem/network/caddy.png","category":"network"},"network-cisco-router":{"path":"icons/onprem/network/cisco-router.png","category":"network"},"network-cisco-switch-l2":{"path":"icons/onprem/network/cisco-switch-l2.png","category":"network"},"network-cisco-switch-l3":{"path":"icons/onprem/network/cisco-switch-l3.png","category":"network"},"network-consul":{"path":"icons/onprem/network/consul.png","category":"network"},"network-envoy":{"path":"icons/onprem/network/envoy.png","category":"network"},"network-etcd":{"path":"icons/onprem/network/etcd.png","category":"network"},"network-glassfish":{"path":"icons/onprem/network/glassfish.png","category":"network"},"network-gunicorn":{"path":"icons/onprem/network/gunicorn.png","category":"network"},"network-haproxy":{"path":"icons/onprem/network/haproxy.png","category":"network"},"network-internet":{"path":"icons/onprem/network/internet.png","category":"network"},"network-istio":{"path":"icons/onprem/network/istio.png","category":"network"},"network-jbossas":{"path":"icons/onprem/network/jbossas.png","category":"network"},"network-jetty":{"path":"icons/onprem/network/jetty.png","category":"network"},"network-kong":{"path":"icons/onprem/network/kong.png","category":"network"},"network-linkerd":{"path":"icons/onprem/network/linkerd.png","category":"network"},"network-mikrotik":{"path":"icons/onprem/network/mikrotik.png","category":"network"},"network-nginx":{"path":"icons/onprem/network/nginx.png","category":"network"},"network-ocelot":{"path":"icons/onprem/network/ocelot.png","category":"network"},"network-open-service-mesh":{"path":"icons/onprem/network/open-service-mesh.png","category":"network"},"network-opnsense":{"path":"icons/onprem/network/opnsense.png","category":"network"},"network-pfsense":{"path":"icons/onprem/network/pfsense.png","category":"network"},"network-pomerium":{"path":"icons/onprem/network/pomerium.png","category":"network"},"network-powerdns":{"path":"icons/onprem/network/powerdns.png","category":"network"},"network-tomcat":{"path":"icons/onprem/network/tomcat.png","category":"network"},"network-traefik":{"path":"icons/onprem/network/traefik.png","category":"network"},"network-tyk":{"path":"icons/onprem/network/tyk.png","category":"network"},"network-vyos":{"path":"icons/onprem/network/vyos.png","category":"network"},"network-wildfly":{"path":"icons/onprem/network/wildfly.png","category":"network"},"network-yarp":{"path":"icons/onprem/network/yarp.png","category":"network"},"network-zookeeper":{"path":"icons/onprem/network/zookeeper.png","category":"network"},"onprem":{"path":"icons/onprem/onprem.png"},"proxmox-pve":{"path":"icons/onprem/proxmox/pve.png","category":"proxmox"},"queue-activemq":{"path":"icons/onprem/queue/activemq.png","category":"queue"},"queue-celery":{"path":"icons/onprem/queue/celery.png","category":"queue"},"queue-emqx":{"path":"icons/onprem/queue/emqx.png","category":"queue"},"queue-kafka":{"path":"icons/onprem/queue/kafka.png","category":"queue"},"queue-nats":{"path":"icons/onprem/queue/nats.png","category":"queue"},"queue-rabbitmq":{"path":"icons/onprem/queue/rabbitmq.png","category":"queue"},"queue-zeromq":{"path":"icons/onprem/queue/zeromq.png","category":"queue"},"registry-harbor":{"path":"icons/onprem/registry/harbor.png","category":"registry"},"registry-jfrog":{"path":"icons/onprem/registry/jfrog.png","category":"registry"},"search-solr":{"path":"icons/onprem/search/solr.png","category":"search"},"security-bitwarden":{"path":"icons/onprem/security/bitwarden.png","category":"security"},"security-trivy":{"path":"icons/onprem/security/trivy.png","category":"security"},"security-vault":{"path":"icons/onprem/security/vault.png","category":"security"},"storage-ceph":{"path":"icons/onprem/storage/ceph.png","category":"storage"},"storage-ceph-osd":{"path":"icons/onprem/storage/ceph-osd.png","category":"storage"},"storage-glusterfs":{"path":"icons/onprem/storage/glusterfs.png","category":"storage"},"storage-portworx":{"path":"icons/onprem/storage/portworx.png","category":"storage"},"tracing-jaeger":{"path":"icons/onprem/tracing/jaeger.png","category":"tracing"},"tracing-tempo":{"path":"icons/onprem/tracing/tempo.png","category":"tracing"},"vcs-git":{"path":"icons/onprem/vcs/git.png","category":"vcs"},"vcs-gitea":{"path":"icons/onprem/vcs/gitea.png","category":"vcs"},"vcs-github":{"path":"icons/onprem/vcs/github.png","category":"vcs"},"vcs-gitlab":{"path":"icons/onprem/vcs/gitlab.png","category":"vcs"},"vcs-svn":{"path":"icons/onprem/vcs/svn.png","category":"vcs"},"workflow-airflow":{"path":"icons/onprem/workflow/airflow.png","category":"workflow"},"workflow-digdag":{"path":"icons/onprem/workflow/digdag.png","category":"workflow"},"workflow-kubeflow":{"path":"icons/onprem/workflow/kubeflow.png","category":"workflow"},"workflow-nifi":{"path":"icons/onprem/workflow/nifi.png","category":"workflow"}},"aliases":{},"info":{"name":"onprem","total":173,"categories":{"aggregator":["aggregator-fluentd","aggregator-vector"],"analytics":["analytics-beam","analytics-databricks","analytics-dbt","analytics-dremio","analytics-flink","analytics-hadoop","analytics-hive","analytics-metabase","analytics-norikra","analytics-powerbi","analytics-presto","analytics-singer","analytics-spark","analytics-storm","analytics-superset","analytics-tableau","analytics-trino"],"auth":["auth-boundary","auth-buzzfeed-sso","auth-oauth2-proxy"],"cd":["cd-spinnaker","cd-tekton-cli","cd-tekton"],"certificates":["certificates-cert-manager","certificates-lets-encrypt"],"ci":["ci-circleci","ci-concourseci","ci-droneci","ci-github-actions","ci-gitlabci","ci-jenkins","ci-teamcity","ci-travisci","ci-zuulci"],"client":["client-client","client-user","client-users"],"compute":["compute-nomad","compute-server"],"container":["container-containerd","container-crio","container-docker","container-firecracker","container-gvisor","container-k3s","container-lxc","container-rkt"],"database":["database-cassandra","database-clickhouse","database-cockroachdb","database-couchbase","database-couchdb","database-dgraph","database-druid","database-duckdb","database-hbase","database-influxdb","database-janusgraph","database-mariadb","database-mongodb","database-mssql","database-mysql","database-neo4j","database-oracle","database-postgresql","database-qdrant","database-scylla"],"dns":["dns-coredns","dns-powerdns"],"etl":["etl-embulk"],"gitops":["gitops-argocd","gitops-flagger","gitops-flux"],"groupware":["groupware-nextcloud"],"iac":["iac-ansible","iac-atlantis","iac-awx","iac-pulumi","iac-puppet","iac-terraform"],"identity":["identity-dex"],"inmemory":["inmemory-aerospike","inmemory-hazelcast","inmemory-memcached","inmemory-redis"],"logging":["logging-fluentbit","logging-graylog","logging-loki","logging-rsyslog","logging-syslog-ng"],"messaging":["messaging-centrifugo"],"mlops":["mlops-mlflow","mlops-polyaxon"],"monitoring":["monitoring-cortex","monitoring-datadog","monitoring-dynatrace","monitoring-grafana","monitoring-humio","monitoring-mimir","monitoring-nagios","monitoring-newrelic","monitoring-prometheus-operator","monitoring-prometheus","monitoring-sentry","monitoring-splunk","monitoring-thanos","monitoring-zabbix"],"network":["network-ambassador","network-apache","network-bind-9","network-caddy","network-cisco-router","network-cisco-switch-l2","network-cisco-switch-l3","network-consul","network-envoy","network-etcd","network-glassfish","network-gunicorn","network-haproxy","network-internet","network-istio","network-jbossas","network-jetty","network-kong","network-linkerd","network-mikrotik","network-nginx","network-ocelot","network-open-service-mesh","network-opnsense","network-pfsense","network-pomerium","network-powerdns","network-tomcat","network-traefik","network-tyk","network-vyos","network-wildfly","network-yarp","network-zookeeper"],"proxmox":["proxmox-pve"],"queue":["queue-activemq","queue-celery","queue-emqx","queue-kafka","queue-nats","queue-rabbitmq","queue-zeromq"],"registry":["registry-harbor","registry-jfrog"],"search":["search-solr"],"security":["security-bitwarden","security-trivy","security-vault"],"storage":["storage-ceph-osd","storage-ceph","storage-glusterfs","storage-portworx"],"tracing":["tracing-jaeger","tracing-tempo"],"vcs":["vcs-git","vcs-gitea","vcs-github","vcs-gitlab","vcs-svn"],"workflow":["workflow-airflow","workflow-digdag","workflow-kubeflow","workflow-nifi"]}}}